divisor.v
module divisor (
    input [2:0] portA,portB,
    input clk,
    input init,
    input rst,
    output reg [2:0] D,M,
    output reg done 
);

reg[2:0] status;
reg [2:0] DV,DR,A = 3'b000;
reg SH_DC;
reg subs;
reg [1:0] ct;
wire LT;
wire z;


//Registro desplazamiento
always @(posedge clk) begin
    if(rst) begin
      DV = portA;
      DR = portB;  
      {A,DV} = {3'b000,DV};  
    end
    else begin
        if (SH_DC) begin
            {A,DV} = {A,DV}<<1;
        end
    end
end
//Contador decreciente
always @(posedge clk) begin
    if(rst) begin
      ct = 3;  
    end
    else begin
        if (SH_DC) begin
            ct = ct-1;
        end
    end
end
//comparador 1
assign LT = (A<DR)? 1 : 0;
//restador
always @(posedge clk) begin
    begin
        if (subs) begin
            A = A - DR;
        end
    end
end
//Comparador 2
assign z=(ct==0)? 1 : 0;


//FSM
parameter START=0, SHIFT_DEC=1, NOTSUBS=2, SUBS=3, END=4;

always @(posedge clk) begin
    case(status)
    START: begin
        SH_DC=0;
        subs=0;
        done=0;
        if(init) begin
            status=SHIFT_DEC;
        end
    end
    SHIFT_DEC: begin
        SH_DC=1;
        subs=0;
        done=0;
        if(LT) status=NOTSUBS;
        else   status=SUBS;
    end
    NOTSUBS: begin
        SH_DC=0;
        subs=0;
        done=0;
        DV[0]=0;
        if(z) status=END;
        else  status=SHIFT_DEC;
    end
    SUBS: begin
        SH_DC=0;
        subs=1;
        done=0;
        DV[0]=1;
        if(z) status=END;
        else  status=SHIFT_DEC;
    end
    END: begin
        SH_DC=0;
        subs=0;
        D = DV;
        M = A;
        done=1; 
    end
    default:
        status=START;
    endcase
end

endmodule

divisor_tb.v
`timescale 1ns / 1ps
`include "divisor.v"

module test;

reg clk, init, rst;
reg [2:0] portA,portB;
wire [2:0] D,M;
wire done;

divisor uut (.portA(portA),.portB(portB),.clk(clk),.init(init),.rst(rst),.D(D),.M(M),.done(done));

initial begin

    $dumpfile("divisor_tb.vcd");
    $dumpvars(0,test);

    portA = 7;
    portB = 2;
    clk=0;
    init=0;
    rst=0;

    #1 assign rst=1;
    #2 assign rst=0;
    #4 init=1;
    #1 init = 0;
    #200 $finish;

end
always #1 clk = ~clk;
endmodule

divisor_tb.vcd
$date
	Sun Apr 24 17:08:26 2022
$end
$version
	Icarus Verilog
$end
$timescale
	1ps
$end
$scope module test $end
$var wire 1 ! done $end
$var wire 3 " M [2:0] $end
$var wire 3 # D [2:0] $end
$var reg 1 $ clk $end
$var reg 1 % init $end
$var reg 3 & portA [2:0] $end
$var reg 3 ' portB [2:0] $end
$var reg 1 ( rst $end
$scope module uut $end
$var wire 1 $ clk $end
$var wire 1 % init $end
$var wire 3 ) portA [2:0] $end
$var wire 3 * portB [2:0] $end
$var wire 1 ( rst $end
$var wire 1 + z $end
$var wire 1 , LT $end
$var reg 3 - A [2:0] $end
$var reg 3 . D [2:0] $end
$var reg 3 / DR [2:0] $end
$var reg 3 0 DV [2:0] $end
$var reg 3 1 M [2:0] $end
$var reg 1 2 SH_DC $end
$var reg 2 3 ct [1:0] $end
$var reg 1 ! done $end
$var reg 3 4 status [2:0] $end
$var reg 1 5 subs $end
$upscope $end
$upscope $end
$enddefinitions $end
#0
$dumpvars
x5
bx 4
bx 3
x2
bx 1
bx 0
bx /
bx .
b0 -
x,
x+
b10 *
b111 )
0(
b10 '
b111 &
0%
0$
bx #
bx "
x!
$end
#1000
1,
0+
b10 /
b111 0
b11 3
b0 4
1$
1(
#2000
0$
#3000
0!
05
02
1$
0(
#4000
0$
#5000
1$
#6000
0$
#7000
b1 4
1$
1%
#8000
0$
0%
#9000
b1 -
b110 0
b10 3
b10 4
12
1$
#10000
0$
#11000
0,
b1 4
02
b1 3
b11 -
b100 0
1$
#12000
0$
#13000
1+
b111 -
b0 0
b0 3
b11 4
12
1$
#14000
0$
#15000
0+
b100 4
b1 0
15
02
b11 3
b110 -
1$
#16000
0$
#17000
1!
b110 "
b110 1
b1 #
b1 .
05
1$
