divisor.v
    module divisor (
        input [2:0] portA,portB,
        input clk,
        input START,
        output reg [2:0] DV,
        output reg DONE
    );

    reg[3:0] status, next_status;
    reg [2:0] DR,A;
    reg INIT;
    reg LDA;
    reg DV0;
    reg SH_DC;
    reg DV0_WRITE;
    reg [2:0] ct;
    wire LT;
    wire z;


    //Registros
    always @(LDA, INIT, SH_DC , DV0_WRITE) begin
        if(INIT) begin
        DV = portA;
        DR = portB;  
        A = 3'b000;
        end

        if (SH_DC) begin
                A=A<<1;
                A[0]=DV[2];
                DV=DV<<1;
            // {A,DV} = {A,DV}<<1;
            end        
        if(DV0_WRITE) 
            DV[0]=DV0;

        if(LDA) 
                A=A-DR;


      
    end 

    //Contador decreciente
    always @(INIT, SH_DC) begin
        if(INIT) begin
        ct = 3;  
        end
        else  if(ct!=0 && SH_DC) begin
                ct=ct-1; 
        end
    end


    //comparador 1
    assign LT = (A<DR)? 1 : 0;




    //Comparador 2
    assign z=(ct==0)? 1 : 0;


    //FSM
    parameter START_S=0, SHIFT_DEC=1, NOTADD=2, ADD=3, END1=4;


    always@(posedge clk) begin
    case(status)
		START_S: begin
            if(START) begin
                next_status=SHIFT_DEC;
            end
        end
        SHIFT_DEC: begin
            if(LT)
            next_status=NOTADD;
            else
            next_status=ADD;
        end
        NOTADD: begin

        if(z)  
            next_status=END1;
           
        else 
            next_status=SHIFT_DEC;
        end
        ADD: begin

            if(z) 
                next_status=END1;
        
            else 
                next_status=SHIFT_DEC;
                
        
        end
        END1: begin
            next_status=END1;
        end
        
        default: next_status=START_S;
        endcase
  end

    always @(status ) begin
        case(status)
        START_S: begin
            SH_DC=0;
            LDA=0;
            DONE=0;
            INIT=1;
            DV0=0;
            DV0_WRITE=0;
        end
        SHIFT_DEC: begin
            SH_DC=1;
            LDA=0;
            DONE=0;
            INIT=0;
            DV0=DV0;
            DV0_WRITE=0;
        end
        NOTADD: begin
            SH_DC=0;
            LDA=0;
            DONE=0;
            INIT=0;
            DV0=0;
            DV0_WRITE=1;

        end
        ADD: begin
            SH_DC=0;
            LDA=1;
            DONE=0;
            INIT=0;
            DV0=1;      
            DV0_WRITE=1;  	  
        end
        END1: begin
            SH_DC=0;
            LDA=0;
            DONE=1;
            INIT=0;
            DV0=0;
            DV0_WRITE=0;
        end
        
        default: DONE=0;
        endcase
    end

    always@(posedge clk) begin
        status=next_status;
    end
    endmodule

divisor_tb.v
`timescale 1ns / 1ps
module test;

reg clk, init;
reg [2:0] portA,portB;
reg START;
wire [2:0] DV;
wire done;

divisor uut (.portA(portA),.portB(portB),.clk(clk),.START(START),.DV(DV),.DONE(DOO));

initial begin

    $dumpfile("divisor_tb.vcd");
    $dumpvars(0,test);

    portA = 4;
    portB = 4;
    clk=0;
    START=0;

    #18 START=1;
    #2000 $finish;

end
always #1 clk = ~clk;
endmodule

divisor_tb.vcd
$date
	Mon Apr 25 20:15:09 2022
$end
$version
	Icarus Verilog
$end
$timescale
	1ps
$end
$scope module test $end
$var wire 3 ! DV [2:0] $end
$var wire 1 " DOO $end
$var reg 1 # START $end
$var reg 1 $ clk $end
$var reg 3 % portA [2:0] $end
$var reg 3 & portB [2:0] $end
$scope module uut $end
$var wire 1 # START $end
$var wire 1 $ clk $end
$var wire 3 ' portA [2:0] $end
$var wire 3 ( portB [2:0] $end
$var wire 1 ) z $end
$var wire 1 * LT $end
$var reg 3 + A [2:0] $end
$var reg 1 " DONE $end
$var reg 3 , DR [2:0] $end
$var reg 3 - DV [2:0] $end
$var reg 1 . DV0 $end
$var reg 1 / DV0_WRITE $end
$var reg 1 0 INIT $end
$var reg 1 1 LDA $end
$var reg 1 2 SH_DC $end
$var reg 3 3 ct [2:0] $end
$var reg 4 4 next_status [3:0] $end
$var reg 4 5 status [3:0] $end
$upscope $end
$upscope $end
$enddefinitions $end
#0
$dumpvars
bx 5
bx 4
bx 3
x2
x1
x0
x/
x.
bx -
bx ,
bx +
x*
x)
b100 (
b100 '
b100 &
b100 %
0$
0#
x"
bx !
$end
#1000
b0 4
1$
#2000
0$
#3000
0)
1*
b11 3
b0 +
b100 ,
b100 !
b100 -
0/
0.
10
0"
01
02
b0 5
1$
#4000
0$
#5000
1$
#6000
0$
#7000
1$
#8000
0$
#9000
1$
#10000
0$
#11000
1$
#12000
0$
#13000
1$
#14000
0$
#15000
1$
#16000
0$
#17000
1$
#18000
0$
1#
#19000
b10 3
b0 !
b0 -
b1 +
00
12
b1 5
b1 4
1$
#20000
0$
#21000
b10 4
1$
#22000
0$
#23000
1/
02
b10 5
1$
#24000
0$
#25000
b1 4
1$
#26000
0$
#27000
b1 3
b10 +
0/
12
b1 5
1$
#28000
0$
#29000
b10 4
1$
#30000
0$
#31000
1/
02
b10 5
1$
#32000
0$
#33000
b1 4
1$
#34000
0$
#35000
1)
0*
b0 3
b100 +
0/
12
b1 5
1$
#36000
0$
#37000
b11 4
1$
#38000
0$
#39000
1*
b0 +
b1 !
b1 -
1/
1.
11
02
b11 5
1$
#40000
0$
#41000
b100 4
1$
#42000
0$
#43000
0/
0.
1"
01
b100 5
1$
